__init__.py
pcio.cp313-win_amd64.pyd
pcio-1.1.1.dist-info/licenses/LICENSE
pcio-1.1.1.dist-info/METADATA
pcio-1.1.1.dist-info/WHEEL
pcio-1.1.1.dist-info/top_level.txt
pcio-1.1.1.dist-info/RECORD
