Metadata-Version: 2.4
Name: pcio
Version: 1.1.1
Summary: Programming contest input/output module
Author: Andrey Demidov
License: MIT License
Keywords: input,print,contest
Classifier: License :: OSI Approved :: MIT License
Classifier: Programming Language :: Python
Classifier: Programming Language :: Python :: 3
Requires-Python: >=3.12
License-File: LICENSE
Dynamic: license-file
